[{"display_html":"<span class=\"keyword\">data</span> <a href=\"#t:Term\">Term</a><ul class=\"subs\"><li>= <a href=\"#v:Num\">Num</a> <a href=\"../base-4.12.0.0/Data-Int.html#t:Int\" title=\"Data.Int\">Int</a></li><li>| <a href=\"#v:Double\">Double</a> <a href=\"Ch01Ex01.html#t:Term\" title=\"Ch01Ex01\">Term</a></li><li>| <a href=\"#v:Add\">Add</a> <a href=\"Ch01Ex01.html#t:Term\" title=\"Ch01Ex01\">Term</a> <a href=\"Ch01Ex01.html#t:Term\" title=\"Ch01Ex01\">Term</a></li></ul>","name":"Term Add Num Double","module":"Ch01Ex01","link":"Ch01Ex01.html#t:Term"},{"display_html":"<a href=\"#v:redSeqs\">redSeqs</a> :: <a href=\"Ch01Ex01.html#t:Term\" title=\"Ch01Ex01\">Term</a> -&gt; [[<a href=\"Ch01Ex01.html#t:Term\" title=\"Ch01Ex01\">Term</a>]]","name":"redSeqs","module":"Ch01Ex01","link":"Ch01Ex01.html#v:redSeqs"},{"display_html":"<a href=\"#v:step\">step</a> :: <a href=\"Ch01Ex01.html#t:Term\" title=\"Ch01Ex01\">Term</a> -&gt; [<a href=\"Ch01Ex01.html#t:Term\" title=\"Ch01Ex01\">Term</a>]","name":"step","module":"Ch01Ex01","link":"Ch01Ex01.html#v:step"},{"display_html":"<a href=\"#v:sum\">sum</a> :: <a href=\"../base-4.12.0.0/Prelude.html#t:Num\" title=\"Prelude\">Num</a> p =&gt; [p] -&gt; p","name":"sum","module":"Ch01Ex02","link":"Ch01Ex02.html#v:sum"},{"display_html":"<a href=\"#v:product\">product</a> :: <a href=\"../base-4.12.0.0/Prelude.html#t:Num\" title=\"Prelude\">Num</a> p =&gt; [p] -&gt; p","name":"product","module":"Ch01Ex03","link":"Ch01Ex03.html#v:product"},{"display_html":"<a href=\"#v:someFunc\">someFunc</a> :: <a href=\"../base-4.12.0.0/System-IO.html#t:IO\" title=\"System.IO\">IO</a> ()","name":"someFunc","module":"Lib","link":"Lib.html#v:someFunc"}]